drio/__init__.py
drio-0.0.1.dist-info/METADATA
drio-0.0.1.dist-info/WHEEL
drio-0.0.1.dist-info/top_level.txt
drio-0.0.1.dist-info/RECORD
