Metadata-Version: 2.4
Name: drio
Version: 0.0.1
Summary: Dummy lock package for drio
Author: AutoPublisher
